{
  "c": "c",
  "throw err": "throw err",
  "write something": "",
  "Введіть логін": "Введіть логін",
  "Введіть нік": "Введіть нік",
  "Введіть пароль": "Введіть пароль",
  "Виникла не передбачуванна помилка": "Occurred an unexpected error",
  "Головна": "Головна",
  "Оновити сторінку": "Refresh page",
  "Про сайт": "Про сайт",
  "Произошла непредвиденная ошибка": "Произошла непредвиденная ошибка",
  "Ст": "Ст",
  "Створити помилку": "Створити помилку",
  "Сторінка не знайдена": "Сторінка не знайдена",
  "Увійти": "Увійти",
  "Форма авторизації": "Форма авторизації"
}
